openssh_key/__init__.py
openssh_key/cryptography_interop.py
openssh_key/excs.py
openssh_key/keyfile.py
openssh_key/keypair.py
openssh_key/openssh_io.py
openssh_key/private_keys.py
openssh_key-0.3.0.dist-info/METADATA
openssh_key-0.3.0.dist-info/WHEEL
openssh_key-0.3.0.dist-info/licenses/LICENSE
openssh_key-0.3.0.dist-info/RECORD
