Metadata-Version: 2.1
Name: openssh-key
Version: 0.3.0
Summary: Tools to deal with OpenSSH2 (RFC4716) keys
Project-URL: Homepage, https://github.com/valohai/openssh_key
Author: Valohai
Maintainer-email: Aarni Koskela <akx@iki.fi>
License-Expression: MIT
License-File: LICENSE
Requires-Python: >=3.7
Provides-Extra: convert
Requires-Dist: cryptography; extra == 'convert'
Provides-Extra: dev
Requires-Dist: pytest-cov; extra == 'dev'
